colorhash/__init__.py
colorhash/colorhash.py
colorhash/py.typed
colorhash-1.3.2.dist-info/METADATA
colorhash-1.3.2.dist-info/WHEEL
colorhash-1.3.2.dist-info/RECORD
