Metadata-Version: 2.1
Name: colorhash
Version: 1.3.2
Summary: Generate color based on any object
Project-URL: Homepage, https://github.com/dimostenis/color-hash-python
Project-URL: Bug Tracker, https://github.com/dimostenis/color-hash-python/issues
Author-email: dimostenis <dimosh3k@gmail.com>, Felix Krull <f_krull@gmx.de>
License: MIT
Keywords: color,hash,hex,hsl,rgb
Requires-Python: >=3.6
Provides-Extra: dev
Requires-Dist: black; extra == 'dev'
Requires-Dist: pre-commit; extra == 'dev'
Requires-Dist: pytest; extra == 'dev'
